bedtime/__init__.py
bedtime/__main__.py
bedtime/common.py
bedtime/macos.py
bedtime/windows.py
Bedtime-0.0.3.dist-info/LICENSE
Bedtime-0.0.3.dist-info/METADATA
Bedtime-0.0.3.dist-info/WHEEL
Bedtime-0.0.3.dist-info/top_level.txt
Bedtime-0.0.3.dist-info/RECORD
