Metadata-Version: 2.1
Name: Bedtime
Version: 0.0.3
Author: dunkyl
License: MIT License        
Project-URL: repository, https://github.com/dunkyl/bedtime
Requires-Python: >=3.8
License-File: LICENSE
Requires-Dist: pyobjc ; sys_platform == "darwin"
Requires-Dist: pywin32 ; sys_platform == "win32"
